neutrino_api/__init__.py
neutrino_api/api_error_code.py
neutrino_api/api_response.py
neutrino_api/neutrino_api_client.py
neutrino_api/examples/__init__.py
neutrino_api/examples/bad_word_filter.py
neutrino_api/examples/bin_list_download.py
neutrino_api/examples/bin_lookup.py
neutrino_api/examples/browser_bot.py
neutrino_api/examples/convert.py
neutrino_api/examples/domain_lookup.py
neutrino_api/examples/email_validate.py
neutrino_api/examples/email_verify.py
neutrino_api/examples/geocode_address.py
neutrino_api/examples/geocode_reverse.py
neutrino_api/examples/hlr_lookup.py
neutrino_api/examples/host_reputation.py
neutrino_api/examples/html_clean.py
neutrino_api/examples/html_render.py
neutrino_api/examples/image_resize.py
neutrino_api/examples/image_watermark.py
neutrino_api/examples/ip_blocklist.py
neutrino_api/examples/ip_blocklist_download.py
neutrino_api/examples/ip_info.py
neutrino_api/examples/ip_probe.py
neutrino_api/examples/phone_playback.py
neutrino_api/examples/phone_validate.py
neutrino_api/examples/phone_verify.py
neutrino_api/examples/qr_code.py
neutrino_api/examples/sms_verify.py
neutrino_api/examples/ua_lookup.py
neutrino_api/examples/url_info.py
neutrino_api/examples/verify_security_code.py
neutrino_api_client_requests-4.7.1.dist-info/licenses/LICENSE
neutrino_api_client_requests-4.7.1.dist-info/METADATA
neutrino_api_client_requests-4.7.1.dist-info/WHEEL
neutrino_api_client_requests-4.7.1.dist-info/top_level.txt
neutrino_api_client_requests-4.7.1.dist-info/RECORD
