Metadata-Version: 2.4
Name: neutrino_api_client_requests
Version: 4.7.1
Summary: Neutrino API Python client using the requests HTTP library
Author-email: Neutrino API <ops@neutrinoapi.com>
License: MIT License
Project-URL: Homepage, https://github.com/NeutrinoAPI/neutrino-api-client-requests
Project-URL: Bug Tracker, https://www.neutrinoapi.com/contact-us/
Classifier: Programming Language :: Python :: 3
Classifier: License :: OSI Approved :: MIT License
Classifier: Operating System :: OS Independent
Classifier: Development Status :: 5 - Production/Stable
Classifier: Topic :: Software Development :: Libraries
Classifier: Topic :: Communications :: Telephony
Classifier: Topic :: Scientific/Engineering :: Artificial Intelligence
Classifier: Topic :: Scientific/Engineering :: Information Analysis
Classifier: Topic :: Text Processing :: Filters
Classifier: Topic :: Text Processing :: Markup :: HTML
Classifier: Topic :: Security
Classifier: Topic :: Utilities
Requires-Python: >=3.7
License-File: LICENSE
Requires-Dist: requests<3,>=2.32.3
Dynamic: license-file
